[{"lang": "en", "retweeted_status": {"lang": "en", "text": "I\u2019m looking for a co-blogger who can add photos to interviews and reviews on my website Bookish Fangirl. Retweet please.", "created_at": "Tue Dec 17 10:57:31 +0000 2019", "hashtags": [], "user_mentions": [], "source": "<a href=\"http://twitter.com/download/iphone\" rel=\"nofollow\">Twitter for iPhone</a>", "user": {"profile_use_background_image": true, "id": 373704492, "profile_image_url_https": "https://pbs.twimg.com/profile_images/1104311434123661312/9hSf9q45_normal.jpg", "profile_sidebar_fill_color": "DDEEF6", "geo_enabled": true, "profile_text_color": "333333", "followers_count": 7515, "location": "Massachusetts", "profile_background_color": "C0DEED", "id_str": "373704492", "statuses_count": 145191, "description": "Pansexual writer. Pantheist. Owner of https://t.co/9RzcEVDvXc #VoteThemOut #TheResistance", "friends_count": 7750, "profile_link_color": "9266CC", "profile_image_url": "http://pbs.twimg.com/profile_images/1104311434123661312/9hSf9q45_normal.jpg", "profile_background_image_url_https": "https://abs.twimg.com/images/themes/theme1/bg.png", "profile_banner_url": "https://pbs.twimg.com/profile_banners/373704492/1464170743", "profile_background_image_url": "http://abs.twimg.com/images/themes/theme1/bg.png", "name": "Tanya Contois", "profile_background_tile": true, "favourites_count": 22888, "screen_name": "tanyacontois", "url": "https://t.co/9RzcEVDvXc", "created_at": "Thu Sep 15 02:15:02 +0000 2011", "profile_sidebar_border_color": "C0DEED", "listed_count": 269}, "urls": [], "retweet_count": 4, "id": 1206891164361723904, "favorite_count": 2, "id_str": "1206891164361723904"}, "text": "RT @tanyacontois: I\u2019m looking for a co-blogger who can add photos to interviews and reviews on my website Bookish Fangirl. Retweet please.", "created_at": "Tue Dec 17 10:59:33 +0000 2019", "hashtags": [], "user_mentions": [{"id_str": "373704492", "screen_name": "tanyacontois", "name": "Tanya Contois", "id": 373704492}], "source": "<a href=\"https://mobile.twitter.com\" rel=\"nofollow\">Twitter Web App</a>", "user": {"id": 3699410608, "profile_image_url_https": "https://pbs.twimg.com/profile_images/833352329600573442/uEp0nFnn_normal.jpg", "profile_sidebar_fill_color": "000000", "geo_enabled": true, "profile_text_color": "000000", "followers_count": 332, "location": "Santa Cruz, CA", "profile_background_color": "000000", "id_str": "3699410608", "statuses_count": 470, "description": "Call me Hussain. || Data. Stories. Research. Writing. || Neuroscience. Philosophy. Mathematics. || Running. Yoga. Coffee. || Views are mine. He/him. \u262a\ufe0f", "friends_count": 370, "profile_link_color": "000000", "profile_image_url": "http://pbs.twimg.com/profile_images/833352329600573442/uEp0nFnn_normal.jpg", "profile_background_image_url_https": "https://abs.twimg.com/images/themes/theme1/bg.png", "profile_banner_url": "https://pbs.twimg.com/profile_banners/3699410608/1487736082", "profile_background_image_url": "http://abs.twimg.com/images/themes/theme1/bg.png", "name": "Syed Hussain Ather", "favourites_count": 246, "screen_name": "SHussainAther", "url": "https://t.co/uIoLRCK37L", "created_at": "Fri Sep 18 19:04:58 +0000 2015", "profile_sidebar_border_color": "000000", "listed_count": 7}, "urls": [], "retweet_count": 4, "id": 1206891677207519232, "id_str": "1206891677207519232"}, {"lang": "en", "in_reply_to_user_id": 2316224708, "text": "@philipcball I haven't seen much support for Pinker's arguments among academics. Have you?", "created_at": "Tue Dec 17 10:56:34 +0000 2019", "hashtags": [], "user_mentions": [{"id_str": "2316224708", "screen_name": "philipcball", "name": "Philip Ball", "id": 2316224708}], "source": "<a href=\"https://mobile.twitter.com\" rel=\"nofollow\">Twitter Web App</a>", "in_reply_to_status_id": 1206890138388877314, "in_reply_to_screen_name": "philipcball", "user": {"id": 3699410608, "profile_image_url_https": "https://pbs.twimg.com/profile_images/833352329600573442/uEp0nFnn_normal.jpg", "profile_sidebar_fill_color": "000000", "geo_enabled": true, "profile_text_color": "000000", "followers_count": 332, "location": "Santa Cruz, CA", "profile_background_color": "000000", "id_str": "3699410608", "statuses_count": 470, "description": "Call me Hussain. || Data. Stories. Research. Writing. || Neuroscience. Philosophy. Mathematics. || Running. Yoga. Coffee. || Views are mine. He/him. \u262a\ufe0f", "friends_count": 370, "profile_link_color": "000000", "profile_image_url": "http://pbs.twimg.com/profile_images/833352329600573442/uEp0nFnn_normal.jpg", "profile_background_image_url_https": "https://abs.twimg.com/images/themes/theme1/bg.png", "profile_banner_url": "https://pbs.twimg.com/profile_banners/3699410608/1487736082", "profile_background_image_url": "http://abs.twimg.com/images/themes/theme1/bg.png", "name": "Syed Hussain Ather", "favourites_count": 246, "screen_name": "SHussainAther", "url": "https://t.co/uIoLRCK37L", "created_at": "Fri Sep 18 19:04:58 +0000 2015", "profile_sidebar_border_color": "000000", "listed_count": 7}, "urls": [], "id": 1206890925332385793, "id_str": "1206890925332385793"}, {"lang": "en", "truncated": true, "text": "Hey #WritingCommunity! Use a single line of Python to make a word cloud of text! Make a pretty visual and learn han\u2026 https://t.co/sOEPCFLMdb", "created_at": "Tue Dec 17 10:29:30 +0000 2019", "hashtags": [{"text": "WritingCommunity"}], "user_mentions": [], "source": "<a href=\"https://mobile.twitter.com\" rel=\"nofollow\">Twitter Web App</a>", "user": {"id": 3699410608, "profile_image_url_https": "https://pbs.twimg.com/profile_images/833352329600573442/uEp0nFnn_normal.jpg", "profile_sidebar_fill_color": "000000", "geo_enabled": true, "profile_text_color": "000000", "followers_count": 332, "location": "Santa Cruz, CA", "profile_background_color": "000000", "id_str": "3699410608", "statuses_count": 470, "description": "Call me Hussain. || Data. Stories. Research. Writing. || Neuroscience. Philosophy. Mathematics. || Running. Yoga. Coffee. || Views are mine. He/him. \u262a\ufe0f", "friends_count": 370, "profile_link_color": "000000", "profile_image_url": "http://pbs.twimg.com/profile_images/833352329600573442/uEp0nFnn_normal.jpg", "profile_background_image_url_https": "https://abs.twimg.com/images/themes/theme1/bg.png", "profile_banner_url": "https://pbs.twimg.com/profile_banners/3699410608/1487736082", "profile_background_image_url": "http://abs.twimg.com/images/themes/theme1/bg.png", "name": "Syed Hussain Ather", "favourites_count": 246, "screen_name": "SHussainAther", "url": "https://t.co/uIoLRCK37L", "created_at": "Fri Sep 18 19:04:58 +0000 2015", "profile_sidebar_border_color": "000000", "listed_count": 7}, "urls": [{"url": "https://t.co/sOEPCFLMdb", "expanded_url": "https://twitter.com/i/web/status/1206884114541842432"}], "id": 1206884114541842432, "favorite_count": 4, "id_str": "1206884114541842432"}, {"lang": "es", "in_reply_to_user_id": 1083201770422239233, "text": "@petrillo_author @AliaTisHere Liberalism.", "created_at": "Tue Dec 17 02:29:12 +0000 2019", "hashtags": [], "user_mentions": [{"id_str": "1083201770422239233", "screen_name": "petrillo_author", "name": "James Petrillo", "id": 1083201770422239233}, {"id_str": "924090255644303360", "screen_name": "AliaTisHere", "name": "Al\u00eda T", "id": 924090255644303360}], "source": "<a href=\"https://mobile.twitter.com\" rel=\"nofollow\">Twitter Web App</a>", "in_reply_to_status_id": 1206762884296036352, "in_reply_to_screen_name": "petrillo_author", "user": {"id": 3699410608, "profile_image_url_https": "https://pbs.twimg.com/profile_images/833352329600573442/uEp0nFnn_normal.jpg", "profile_sidebar_fill_color": "000000", "geo_enabled": true, "profile_text_color": "000000", "followers_count": 332, "location": "Santa Cruz, CA", "profile_background_color": "000000", "id_str": "3699410608", "statuses_count": 470, "description": "Call me Hussain. || Data. Stories. Research. Writing. || Neuroscience. Philosophy. Mathematics. || Running. Yoga. Coffee. || Views are mine. He/him. \u262a\ufe0f", "friends_count": 370, "profile_link_color": "000000", "profile_image_url": "http://pbs.twimg.com/profile_images/833352329600573442/uEp0nFnn_normal.jpg", "profile_background_image_url_https": "https://abs.twimg.com/images/themes/theme1/bg.png", "profile_banner_url": "https://pbs.twimg.com/profile_banners/3699410608/1487736082", "profile_background_image_url": "http://abs.twimg.com/images/themes/theme1/bg.png", "name": "Syed Hussain Ather", "favourites_count": 246, "screen_name": "SHussainAther", "url": "https://t.co/uIoLRCK37L", "created_at": "Fri Sep 18 19:04:58 +0000 2015", "profile_sidebar_border_color": "000000", "listed_count": 7}, "urls": [], "id": 1206763242724265984, "favorite_count": 5, "id_str": "1206763242724265984"}, {"lang": "en", "in_reply_to_user_id": 589535421, "text": "@paldhous Would this be an interesting database to analyze? https://t.co/Q73gUoJST4", "created_at": "Mon Dec 16 08:25:51 +0000 2019", "hashtags": [], "user_mentions": [{"id_str": "589535421", "screen_name": "paldhous", "name": "Peter Aldhous", "id": 589535421}], "source": "<a href=\"https://mobile.twitter.com\" rel=\"nofollow\">Twitter Web App</a>", "in_reply_to_screen_name": "paldhous", "user": {"id": 3699410608, "profile_image_url_https": "https://pbs.twimg.com/profile_images/833352329600573442/uEp0nFnn_normal.jpg", "profile_sidebar_fill_color": "000000", "geo_enabled": true, "profile_text_color": "000000", "followers_count": 332, "location": "Santa Cruz, CA", "profile_background_color": "000000", "id_str": "3699410608", "statuses_count": 470, "description": "Call me Hussain. || Data. Stories. Research. Writing. || Neuroscience. Philosophy. Mathematics. || Running. Yoga. Coffee. || Views are mine. He/him. \u262a\ufe0f", "friends_count": 370, "profile_link_color": "000000", "profile_image_url": "http://pbs.twimg.com/profile_images/833352329600573442/uEp0nFnn_normal.jpg", "profile_background_image_url_https": "https://abs.twimg.com/images/themes/theme1/bg.png", "profile_banner_url": "https://pbs.twimg.com/profile_banners/3699410608/1487736082", "profile_background_image_url": "http://abs.twimg.com/images/themes/theme1/bg.png", "name": "Syed Hussain Ather", "favourites_count": 246, "screen_name": "SHussainAther", "url": "https://t.co/uIoLRCK37L", "created_at": "Fri Sep 18 19:04:58 +0000 2015", "profile_sidebar_border_color": "000000", "listed_count": 7}, "urls": [{"url": "https://t.co/Q73gUoJST4", "expanded_url": "https://www.sacbee.com/news/investigations/article237207498.html"}], "id": 1206490611408232448, "id_str": "1206490611408232448"}, {"lang": "en", "in_reply_to_user_id": 1189990033203187712, "truncated": true, "text": "@ImKaitlynMeyers I could delete Mary's parents. Mary herself, the protagonist of my WIP on her psychotherapy sessio\u2026 https://t.co/7dOP7jRAzq", "created_at": "Sat Dec 14 01:28:45 +0000 2019", "hashtags": [], "user_mentions": [{"id_str": "1189990033203187712", "screen_name": "ImKaitlynMeyers", "name": "Kaitlyn Meyers", "id": 1189990033203187712}], "source": "<a href=\"https://mobile.twitter.com\" rel=\"nofollow\">Twitter Web App</a>", "in_reply_to_status_id": 1205657420392828928, "in_reply_to_screen_name": "ImKaitlynMeyers", "user": {"id": 3699410608, "profile_image_url_https": "https://pbs.twimg.com/profile_images/833352329600573442/uEp0nFnn_normal.jpg", "profile_sidebar_fill_color": "000000", "geo_enabled": true, "profile_text_color": "000000", "followers_count": 332, "location": "Santa Cruz, CA", "profile_background_color": "000000", "id_str": "3699410608", "statuses_count": 470, "description": "Call me Hussain. || Data. Stories. Research. Writing. || Neuroscience. Philosophy. Mathematics. || Running. Yoga. Coffee. || Views are mine. He/him. \u262a\ufe0f", "friends_count": 370, "profile_link_color": "000000", "profile_image_url": "http://pbs.twimg.com/profile_images/833352329600573442/uEp0nFnn_normal.jpg", "profile_background_image_url_https": "https://abs.twimg.com/images/themes/theme1/bg.png", "profile_banner_url": "https://pbs.twimg.com/profile_banners/3699410608/1487736082", "profile_background_image_url": "http://abs.twimg.com/images/themes/theme1/bg.png", "name": "Syed Hussain Ather", "favourites_count": 246, "screen_name": "SHussainAther", "url": "https://t.co/uIoLRCK37L", "created_at": "Fri Sep 18 19:04:58 +0000 2015", "profile_sidebar_border_color": "000000", "listed_count": 7}, "urls": [{"url": "https://t.co/7dOP7jRAzq", "expanded_url": "https://twitter.com/i/web/status/1205660867724865536"}], "id": 1205660867724865536, "favorite_count": 1, "id_str": "1205660867724865536"}, {"lang": "en", "in_reply_to_user_id": 1189990033203187712, "text": "@ImKaitlynMeyers My sister\u2019s cat is like that -sleeping on everyone\u2019s lap, following everyone around.", "created_at": "Sat Dec 14 00:35:00 +0000 2019", "hashtags": [], "user_mentions": [{"id_str": "1189990033203187712", "screen_name": "ImKaitlynMeyers", "name": "Kaitlyn Meyers", "id": 1189990033203187712}], "source": "<a href=\"https://mobile.twitter.com\" rel=\"nofollow\">Twitter Web App</a>", "in_reply_to_status_id": 1205646401704562688, "in_reply_to_screen_name": "ImKaitlynMeyers", "user": {"id": 3699410608, "profile_image_url_https": "https://pbs.twimg.com/profile_images/833352329600573442/uEp0nFnn_normal.jpg", "profile_sidebar_fill_color": "000000", "geo_enabled": true, "profile_text_color": "000000", "followers_count": 332, "location": "Santa Cruz, CA", "profile_background_color": "000000", "id_str": "3699410608", "statuses_count": 470, "description": "Call me Hussain. || Data. Stories. Research. Writing. || Neuroscience. Philosophy. Mathematics. || Running. Yoga. Coffee. || Views are mine. He/him. \u262a\ufe0f", "friends_count": 370, "profile_link_color": "000000", "profile_image_url": "http://pbs.twimg.com/profile_images/833352329600573442/uEp0nFnn_normal.jpg", "profile_background_image_url_https": "https://abs.twimg.com/images/themes/theme1/bg.png", "profile_banner_url": "https://pbs.twimg.com/profile_banners/3699410608/1487736082", "profile_background_image_url": "http://abs.twimg.com/images/themes/theme1/bg.png", "name": "Syed Hussain Ather", "favourites_count": 246, "screen_name": "SHussainAther", "url": "https://t.co/uIoLRCK37L", "created_at": "Fri Sep 18 19:04:58 +0000 2015", "profile_sidebar_border_color": "000000", "listed_count": 7}, "urls": [], "id": 1205647338896687105, "favorite_count": 2, "id_str": "1205647338896687105"}, {"lang": "und", "in_reply_to_user_id": 55063, "text": "@jonbeckett Ty !", "created_at": "Sat Dec 14 00:13:17 +0000 2019", "hashtags": [], "user_mentions": [{"id_str": "55063", "screen_name": "jonbeckett", "name": "Jonathan Beckett", "id": 55063}], "source": "<a href=\"https://mobile.twitter.com\" rel=\"nofollow\">Twitter Web App</a>", "in_reply_to_status_id": 1205463732928811018, "in_reply_to_screen_name": "jonbeckett", "user": {"id": 3699410608, "profile_image_url_https": "https://pbs.twimg.com/profile_images/833352329600573442/uEp0nFnn_normal.jpg", "profile_sidebar_fill_color": "000000", "geo_enabled": true, "profile_text_color": "000000", "followers_count": 332, "location": "Santa Cruz, CA", "profile_background_color": "000000", "id_str": "3699410608", "statuses_count": 470, "description": "Call me Hussain. || Data. Stories. Research. Writing. || Neuroscience. Philosophy. Mathematics. || Running. Yoga. Coffee. || Views are mine. He/him. \u262a\ufe0f", "friends_count": 370, "profile_link_color": "000000", "profile_image_url": "http://pbs.twimg.com/profile_images/833352329600573442/uEp0nFnn_normal.jpg", "profile_background_image_url_https": "https://abs.twimg.com/images/themes/theme1/bg.png", "profile_banner_url": "https://pbs.twimg.com/profile_banners/3699410608/1487736082", "profile_background_image_url": "http://abs.twimg.com/images/themes/theme1/bg.png", "name": "Syed Hussain Ather", "favourites_count": 246, "screen_name": "SHussainAther", "url": "https://t.co/uIoLRCK37L", "created_at": "Fri Sep 18 19:04:58 +0000 2015", "profile_sidebar_border_color": "000000", "listed_count": 7}, "urls": [], "id": 1205641874553225216, "id_str": "1205641874553225216"}, {"lang": "en", "in_reply_to_user_id": 1194044247340670977, "text": "@MagicalOverload @MWSchutter My cosplay! https://t.co/PmDDsEJPBj", "created_at": "Fri Dec 13 07:23:00 +0000 2019", "hashtags": [], "user_mentions": [{"id_str": "1194044247340670977", "screen_name": "MagicalOverload", "name": "Magical Overload", "id": 1194044247340670977}, {"id_str": "27535885", "screen_name": "MWSchutter", "name": "Mark Wayne", "id": 27535885}], "source": "<a href=\"https://mobile.twitter.com\" rel=\"nofollow\">Twitter Web App</a>", "in_reply_to_status_id": 1205372572902277121, "in_reply_to_screen_name": "MagicalOverload", "user": {"id": 3699410608, "profile_image_url_https": "https://pbs.twimg.com/profile_images/833352329600573442/uEp0nFnn_normal.jpg", "profile_sidebar_fill_color": "000000", "geo_enabled": true, "profile_text_color": "000000", "followers_count": 332, "location": "Santa Cruz, CA", "profile_background_color": "000000", "id_str": "3699410608", "statuses_count": 470, "description": "Call me Hussain. || Data. Stories. Research. Writing. || Neuroscience. Philosophy. Mathematics. || Running. Yoga. Coffee. || Views are mine. He/him. \u262a\ufe0f", "friends_count": 370, "profile_link_color": "000000", "profile_image_url": "http://pbs.twimg.com/profile_images/833352329600573442/uEp0nFnn_normal.jpg", "profile_background_image_url_https": "https://abs.twimg.com/images/themes/theme1/bg.png", "profile_banner_url": "https://pbs.twimg.com/profile_banners/3699410608/1487736082", "profile_background_image_url": "http://abs.twimg.com/images/themes/theme1/bg.png", "name": "Syed Hussain Ather", "favourites_count": 246, "screen_name": "SHussainAther", "url": "https://t.co/uIoLRCK37L", "created_at": "Fri Sep 18 19:04:58 +0000 2015", "profile_sidebar_border_color": "000000", "listed_count": 7}, "urls": [{"url": "https://t.co/PmDDsEJPBj", "expanded_url": "https://www.instagram.com/shacosplay/"}], "id": 1205387627953655808, "favorite_count": 5, "id_str": "1205387627953655808"}, {"lang": "en", "in_reply_to_user_id": 4100229695, "text": "@jeffobergwrites @ZenaAZellers Let's see if you can get there\n\nhttps://t.co/El03KxqOVu", "created_at": "Fri Dec 13 03:24:14 +0000 2019", "hashtags": [], "user_mentions": [{"id_str": "4100229695", "screen_name": "jeffobergwrites", "name": "J. A. Oberg", "id": 4100229695}, {"id_str": "1173400539729518597", "screen_name": "ZenaAZellers", "name": "Zena A Zellers \ud83c\udf08\ud83d\udd8b\ud83d\udcd6", "id": 1173400539729518597}], "source": "<a href=\"https://mobile.twitter.com\" rel=\"nofollow\">Twitter Web App</a>", "in_reply_to_status_id": 1205311928098263045, "in_reply_to_screen_name": "jeffobergwrites", "user": {"id": 3699410608, "profile_image_url_https": "https://pbs.twimg.com/profile_images/833352329600573442/uEp0nFnn_normal.jpg", "profile_sidebar_fill_color": "000000", "geo_enabled": true, "profile_text_color": "000000", "followers_count": 332, "location": "Santa Cruz, CA", "profile_background_color": "000000", "id_str": "3699410608", "statuses_count": 470, "description": "Call me Hussain. || Data. Stories. Research. Writing. || Neuroscience. Philosophy. Mathematics. || Running. Yoga. Coffee. || Views are mine. He/him. \u262a\ufe0f", "friends_count": 370, "profile_link_color": "000000", "profile_image_url": "http://pbs.twimg.com/profile_images/833352329600573442/uEp0nFnn_normal.jpg", "profile_background_image_url_https": "https://abs.twimg.com/images/themes/theme1/bg.png", "profile_banner_url": "https://pbs.twimg.com/profile_banners/3699410608/1487736082", "profile_background_image_url": "http://abs.twimg.com/images/themes/theme1/bg.png", "name": "Syed Hussain Ather", "favourites_count": 246, "screen_name": "SHussainAther", "url": "https://t.co/uIoLRCK37L", "created_at": "Fri Sep 18 19:04:58 +0000 2015", "profile_sidebar_border_color": "000000", "listed_count": 7}, "urls": [{"url": "https://t.co/El03KxqOVu", "expanded_url": "https://www.youtube.com/watch?v=_ttj9Bd8uOg"}], "id": 1205327543772958720, "favorite_count": 1, "id_str": "1205327543772958720"}]